fuzzy_redirect_mapper/__init__.py
fuzzy_redirect_mapper/redirect_mapper.py
tests/__init__.py
tests/test_redirect_mapper.py
fuzzy_redirect_mapper-0.1.0.dist-info/METADATA
fuzzy_redirect_mapper-0.1.0.dist-info/WHEEL
fuzzy_redirect_mapper-0.1.0.dist-info/entry_points.txt
fuzzy_redirect_mapper-0.1.0.dist-info/top_level.txt
fuzzy_redirect_mapper-0.1.0.dist-info/RECORD
