Metadata-Version: 2.1
Name: fuzzy_redirect_mapper
Version: 0.1.0
Summary: A tool to speed up redirect mapping using fuzzy matching.
Home-page: https://chrisleverseo.com/t/python-fuzzy-multi-format-redirect-builder.147/
Author: Chris Lever SEO
Author-email: hello@chrisleverseo.com
Classifier: Programming Language :: Python :: 3
Classifier: License :: OSI Approved :: MIT License
Classifier: Operating System :: OS Independent
Requires-Python: >=3.6
Requires-Dist: pandas
Requires-Dist: fuzzywuzzy[speedup]
Requires-Dist: python-Levenshtein
